oncoboxlib/__init__.py
oncoboxlib/calculate_scores.py
oncoboxlib/common/math/__init__.py
oncoboxlib/common/math/stat.py
oncoboxlib/quant/database/__init__.py
oncoboxlib/quant/database/database.py
oncoboxlib/quant/database/interfaces.py
oncoboxlib/quant/scoring/__init__.py
oncoboxlib/quant/scoring/samples.py
oncoboxlib/quant/scoring/scores.py
oncoboxlib-1.3.0.dist-info/LICENSE
oncoboxlib-1.3.0.dist-info/METADATA
oncoboxlib-1.3.0.dist-info/WHEEL
oncoboxlib-1.3.0.dist-info/entry_points.txt
oncoboxlib-1.3.0.dist-info/top_level.txt
oncoboxlib-1.3.0.dist-info/RECORD
