Metadata-Version: 2.1
Name: oncoboxlib
Version: 1.3.0
Summary: Oncobox collections of libraries
Author-email: Victor Tkachev <victor.tkachev@yandex.com>, Alexander Simonov <registsys@mail.ru>
License: # Released under MIT License
Project-URL: Homepage, https://gitlab.com/oncobox/oncoboxlib
Project-URL: Bug Tracker, https://gitlab.com/oncobox/oncoboxlib/issues
Keywords: bioinformatics,transcriptomics,pathways
Classifier: Development Status :: 5 - Production/Stable
Classifier: Intended Audience :: Science/Research
Classifier: License :: OSI Approved :: MIT License
Classifier: Operating System :: OS Independent
Classifier: Programming Language :: Python :: 3
Classifier: Programming Language :: Python :: 3.10
Requires-Python: >=3.10
License-File: LICENSE
Requires-Dist: et-xmlfile ==1.1.0
Requires-Dist: numpy ==1.26.2
Requires-Dist: openpyxl ==3.1.2
Requires-Dist: packaging ==23.2
Requires-Dist: pandas ==2.1.3
Requires-Dist: patsy ==0.5.4
Requires-Dist: python-dateutil ==2.8.2
Requires-Dist: pytz ==2023.3.post1
Requires-Dist: scipy ==1.11.4
Requires-Dist: six ==1.16.0
Requires-Dist: statsmodels ==0.14.0
Requires-Dist: tzdata ==2023.3
